<annotation>
	<folder>no-train-230803</folder>
	<filename>20230803-172631.419453.jpg</filename>
	<path>/media/zjj/HDD3/train_data/yolov7/打架/yolo_yolopose_回归/03_/fight-detection-surv-dataset-master/noFight/no-train-230803/20230803-172631.419453.jpg</path>
	<source>
		<database>Unknown</database>
	</source>
	<size>
		<width>320</width>
		<height>240</height>
		<depth>3</depth>
	</size>
	<segmented>0</segmented>
	<object>
		<name>normal</name>
		<pose>Unspecified</pose>
		<truncated>1</truncated>
		<difficult>0</difficult>
		<bndbox>
			<xmin>287</xmin>
			<ymin>69</ymin>
			<xmax>320</xmax>
			<ymax>140</ymax>
		</bndbox>
	</object>
	<object>
		<name>normal</name>
		<pose>Unspecified</pose>
		<truncated>0</truncated>
		<difficult>0</difficult>
		<bndbox>
			<xmin>174</xmin>
			<ymin>6</ymin>
			<xmax>189</xmax>
			<ymax>36</ymax>
		</bndbox>
	</object>
</annotation>
