<annotation>
	<folder>images</folder>
	<filename>nv293_3.jpg</filename>
	<path>/media/leka/ACB034F7B034C99A/codes/yolov7-main/data/fight_data/images/nv293_3.jpg</path>
	<source>
		<database>Unknown</database>
	</source>
	<size>
		<width>1280</width>
		<height>720</height>
		<depth>3</depth>
	</size>
	<segmented>0</segmented>
	<object>
		<name>normal</name>
		<pose>Unspecified</pose>
		<truncated>1</truncated>
		<difficult>0</difficult>
		<bndbox>
			<xmin>609</xmin>
			<ymin>139</ymin>
			<xmax>889</xmax>
			<ymax>720</ymax>
		</bndbox>
	</object>
	<object>
		<name>normal</name>
		<pose>Unspecified</pose>
		<truncated>0</truncated>
		<difficult>0</difficult>
		<bndbox>
			<xmin>867</xmin>
			<ymin>161</ymin>
			<xmax>1066</xmax>
			<ymax>680</ymax>
		</bndbox>
	</object>
</annotation>
