<annotation>
	<folder>frame_with_skeleton</folder>
	<filename>skele_006.jpg</filename>
	<path>/media/leka/4C66421F664209E2/score-rgb/skele/frame_with_skeleton/skele_006.jpg</path>
	<source>
		<database>Unknown</database>
	</source>
	<size>
		<width>654</width>
		<height>918</height>
		<depth>3</depth>
	</size>
	<segmented>0</segmented>
	<object>
		<name>fighting</name>
		<pose>Unspecified</pose>
		<truncated>1</truncated>
		<difficult>0</difficult>
		<bndbox>
			<xmin>12</xmin>
			<ymin>80</ymin>
			<xmax>538</xmax>
			<ymax>918</ymax>
		</bndbox>
	</object>
</annotation>
