<annotation>
	<folder>images</folder>
	<filename>ubi_normal_skele_051.jpg</filename>
	<path>/media/leka/4C66421F664209E2/skeleton_data/images/ubi_normal_skele_051.jpg</path>
	<source>
		<database>Unknown</database>
	</source>
	<size>
		<width>640</width>
		<height>360</height>
		<depth>3</depth>
	</size>
	<segmented>0</segmented>
	<object>
		<name>normal</name>
		<pose>Unspecified</pose>
		<truncated>0</truncated>
		<difficult>0</difficult>
		<bndbox>
			<xmin>142</xmin>
			<ymin>43</ymin>
			<xmax>213</xmax>
			<ymax>234</ymax>
		</bndbox>
	</object>
	<object>
		<name>normal</name>
		<pose>Unspecified</pose>
		<truncated>0</truncated>
		<difficult>0</difficult>
		<bndbox>
			<xmin>230</xmin>
			<ymin>54</ymin>
			<xmax>331</xmax>
			<ymax>210</ymax>
		</bndbox>
	</object>
</annotation>
